odoo9_addon_account_enterprise_remove-9.0.1.0.0-py2.7-nspkg.pth
odoo9_addon_account_enterprise_remove-9.0.1.0.0.dist-info/top_level.txt
odoo9_addon_account_enterprise_remove-9.0.1.0.0.dist-info/WHEEL
odoo9_addon_account_enterprise_remove-9.0.1.0.0.dist-info/RECORD
odoo9_addon_account_enterprise_remove-9.0.1.0.0.dist-info/metadata.json
odoo9_addon_account_enterprise_remove-9.0.1.0.0.dist-info/DESCRIPTION.rst
odoo9_addon_account_enterprise_remove-9.0.1.0.0.dist-info/METADATA
odoo9_addon_account_enterprise_remove-9.0.1.0.0.dist-info/namespace_packages.txt
odoo_addons/account_enterprise_remove/__openerp__.py
odoo_addons/account_enterprise_remove/__init__.py
odoo_addons/account_enterprise_remove/README.rst
odoo_addons/account_enterprise_remove/views/res_config_view.xml
odoo_addons/account_enterprise_remove/static/description/icon.png
